Leer_PDF/Funciones.py
Leer_PDF/__init__.py
Leer_PDF-1.0.0.dist-info/METADATA
Leer_PDF-1.0.0.dist-info/WHEEL
Leer_PDF-1.0.0.dist-info/top_level.txt
Leer_PDF-1.0.0.dist-info/RECORD
